{
  "appid": "wx365790a8c04e3a3b",
  "compileType": "miniprogram",
  "libVersion": "2.31.0",
  "packOptions": {
    "ignore": [],
    "include": []
  },
  "setting": {
    "packNpmManually": true,
    "packNpmRelationList": [
      {
        "packageJsonPath": "./package.json",
        "miniprogramNpmDistDir": "./"
      }
    ],
    "babelSetting": {
      "ignore": [],
      "disablePlugins": [],
      "outputPath": ""
    },
    "condition": false,
    "es6": false,
    "enhance": false
  },
  "condition": {},
  "editorSetting": {
    "tabIndent": "insertSpaces",
    "tabSize": 2
  },
  "projectname": "code"
}